labmate/__config__.py
labmate/__init__.py
labmate/acquisition/__init__.py
labmate/acquisition/acquisition_data.py
labmate/acquisition/acquisition_loop.py
labmate/acquisition/acquisition_manager.py
labmate/acquisition/analysis_data.py
labmate/acquisition/analysis_loop.py
labmate/acquisition/backend.py
labmate/acquisition/config_file.py
labmate/acquisition/custom_lint.py
labmate/acquisition_notebook/__init__.py
labmate/acquisition_notebook/acquisition_analysis_manager.py
labmate/acquisition_notebook/display_widget.py
labmate/attrdict/__init__.py
labmate/attrdict/attrdict_class.py
labmate/display/__init__.py
labmate/display/buttons.py
labmate/display/html_output.py
labmate/display/links.py
labmate/display/main.py
labmate/display/platform_utils/__init__.py
labmate/display/platform_utils/windows_utils.py
labmate/logger/__init__.py
labmate/parsing/__init__.py
labmate/parsing/brackets_score.py
labmate/parsing/parsed_value.py
labmate/parsing/saving.py
labmate/utils/__init__.py
labmate/utils/async_utils.py
labmate/utils/autoreload.py
labmate/utils/errors.py
labmate/utils/file_read.py
labmate/utils/lint.py
labmate/utils/random_utils.py
labmate/utils/title_parsing.py
labmate-0.10.5.dist-info/licenses/LICENCE
labmate-0.10.5.dist-info/METADATA
labmate-0.10.5.dist-info/WHEEL
labmate-0.10.5.dist-info/top_level.txt
labmate-0.10.5.dist-info/RECORD
