Metadata-Version: 2.4
Name: labmate
Version: 0.10.5
Summary: Data management library to save data and plots to hdf5 files
Home-page: https://github.com/kyrylo-gr/labmate
Author: kyrylo.gr | LKB-OMQ
Author-email: git@kyrylo.gr
Classifier: Programming Language :: Python :: 3
Classifier: Operating System :: OS Independent
Requires-Python: >=3.8
License-File: LICENCE
Requires-Dist: numpy
Requires-Dist: dh5
Provides-Extra: all
Requires-Dist: matplotlib; extra == "all"
Requires-Dist: pltsave; extra == "all"
Provides-Extra: dev
Requires-Dist: matplotlib; extra == "dev"
Requires-Dist: pytest; extra == "dev"
Requires-Dist: check-manifest; extra == "dev"
Requires-Dist: sphinx; extra == "dev"
Requires-Dist: sphinx_rtd_theme; extra == "dev"
Dynamic: author
Dynamic: author-email
Dynamic: classifier
Dynamic: description
Dynamic: description-content-type
Dynamic: home-page
Dynamic: license-file
Dynamic: provides-extra
Dynamic: requires-dist
Dynamic: requires-python
Dynamic: summary
